jupyter_images/__init__.py
jupyter_images-0.1.dist-info/METADATA
jupyter_images-0.1.dist-info/WHEEL
jupyter_images-0.1.dist-info/top_level.txt
jupyter_images-0.1.dist-info/RECORD
