Metadata-Version: 2.1
Name: jupyter-images
Version: 0.1
Summary: package for generating HTML code to put images in Jupyter notebooks, especially from google drive
Home-page: https://github.com/ryanGT/jupyter_images
Author: Ryan Krauss
Author-email: ryanwkrauss@gmail.com
License: UNKNOWN
Platform: UNKNOWN
Classifier: Programming Language :: Python :: 3
Classifier: License :: OSI Approved :: MIT License
Classifier: Operating System :: OS Independent
